django_client_manager/__init__.py
django_client_manager/django_client.py
django_client_manager-1.0.dist-info/LICENSE
django_client_manager-1.0.dist-info/METADATA
django_client_manager-1.0.dist-info/WHEEL
django_client_manager-1.0.dist-info/top_level.txt
django_client_manager-1.0.dist-info/RECORD
