Metadata-Version: 2.1
Name: django-client-manager
Version: 1.0
Summary: A Client manager for custom django user.
Home-page: https://github.com/pyquinnnarlo/django-client-manager
Author: Quinn Narlo
Author-email: pyquinnnarlo@gmail.com
License: UNKNOWN
Project-URL: Source, https://github.com/pyquinnnarlo/django-client-manager
Keywords: django client manager
Platform: UNKNOWN
Classifier: Programming Language :: Python :: 3
Classifier: Framework :: Django
Classifier: License :: OSI Approved :: MIT License
Classifier: Operating System :: OS Independent
License-File: LICENSE
Requires-Dist: django
